{
    "イラッシャル": {
        "常体": "来る",
        "段-行": "カ行変格"
    },
    "ウカガウ": {
        "常体": "行く",
        "段-行": "五段-ワア行"
    },
    "オッシャル": {
        "常体": "言う",
        "段-行": "五段-ワア行"
    },
    "オボシメス": {
        "常体": "思う",
        "段-行": "五段-ワア行"
    },
    "カケ": {
        "常体": "座る",
        "段-行": "五段-ラ行"
    },
    "カシコマル": {
        "常体": "分かる",
        "段-行": "五段-ラ行"
    },
    "コス": {
        "常体": "来る",
        "段-行": "カ行変格"
    },
    "ゾンジル": {
        "常体": "知る",
        "段-行": "上一段-ザ行"
    },
    "ゾンジアゲル": {
        "常体": "知る",
        "段-行": "上一段-ザ行"
    },
    "タマワル": {
        "常体": "もらう",
        "段-行": "五段-ワア行"
    },
    "チョウダイ": {
        "常体": "もらう",
        "段-行": "五段-ワア行"
    },
    "テラッシャル": {
        "常体": "ている",
        "段-行": "上一段-ア行"
    },
    "ナサル": {
        "常体": "する",
        "段-行": "サ行変格"
    },
    "ハイケン": {
        "常体": "見る",
        "段-行": "上一段-マ行"
    },
    "ハイサツ": {
        "常体": "思う",
        "段-行": "五段-ワア行"
    },
    "ハイジュ": {
        "常体": "もらう",
        "段-行": "五段-ワア行"
    },
    "ハイチョウ": {
        "常体": "聴く",
        "段-行": "五段-カ行"
    },
    "ハイドク": {
        "常体": "読む",
        "段-行": "五段-マ行"
    },
    "マイル": {
        "常体": "行く",
        "段-行": "五段-ラ行"
    },
    "メシアガル": {
        "常体": "食べる",
        "段-行": "下一段-バ行"
    },
    "モウス": {
        "常体": "言う",
        "段-行": "五段-ワア行"
    },
    "モウシアゲル": {
        "常体": "言う",
        "段-行": "五段-ワア行"
    },
    "モトメル": {
        "常体": "買う",
        "段-行": "五段-ワア行"
    },
    "メシ": {
        "常体": "着る",
        "段-行": "上一段-カ行"
    },
    "ラン": {
        "常体": "見る",
        "段-行": "上一段-マ行"
    }


}
